{
  "$schema": "../../node_modules/@angular/service-worker/config/schema.json",
  "index": "./establishment-public/welcome-index.html",
  "assetGroups": [
    {
      "name": "app",
      "installMode": "prefetch",
      "resources": {
        "files": [
          "./establishment-public/favicon.ico",
          "./establishment-public/welcome-index.html",
          "./establishment-public/manifest.webmanifest",
          "./establishment-public/*.css",
          "./establishment-public/*.js"
        ]
      }
    },
    {
      "name": "assets",
      "installMode": "lazy",
      "updateMode": "prefetch",
      "resources": {
        "files": [
          "./establishment-public/assets/**",
          "./establishment-public/*.(eot|svg|cur|jpg|png|webp|gif|otf|ttf|woff|woff2|ani)"
        ]
      }
    }
  ]
}
